{
"type": "FeatureCollection",
"name": "TiyikKoordinat Warkop",
"crs": { "type": "name", "properties": { "name": "urn:ogc:def:crs:OGC:1.3:CRS84" } },
"features": [
{ "type": "Feature", "properties": { "NO": true, "WARKOP": "Warkop Meqar", "X": 120.4675009, "Y": -6.1166485 }, "geometry": { "type": "Point", "coordinates": [ 120.4675009, -6.1166485 ] } }
]
}
